example1249_p0/__init__.py
example1249_p0/main_pkg/__init__.py
example1249_p0/main_pkg/t4.py
example1249_p0-0.0.1.dist-info/METADATA
example1249_p0-0.0.1.dist-info/WHEEL
example1249_p0-0.0.1.dist-info/top_level.txt
example1249_p0-0.0.1.dist-info/RECORD
